altdphi/__init__.py
altdphi/_version.py
altdphi/altdphi.py
altdphi-1.0.5.dist-info/LICENSE
altdphi-1.0.5.dist-info/METADATA
altdphi-1.0.5.dist-info/WHEEL
altdphi-1.0.5.dist-info/top_level.txt
altdphi-1.0.5.dist-info/RECORD
