Metadata-Version: 2.1
Name: altdphi
Version: 1.0.5
Summary: A library for calculating alternative variables for background rejection in new physics searches with missing transverse momentum at LHC
Home-page: http://altdphi.readthedocs.io
Author: Tai Sakuma
Author-email: tai.sakuma@gmail.com
License: UNKNOWN
Platform: UNKNOWN
Classifier: Development Status :: 5 - Production/Stable
Classifier: Intended Audience :: Science/Research
Classifier: License :: OSI Approved :: BSD License
Classifier: Programming Language :: Python :: 2.7
Classifier: Programming Language :: Python :: 3.6
Classifier: Programming Language :: Python :: 3.7
Requires-Dist: numpy
